README.md
setup.py
mopidy_mopidy/__init__.py
mopidy_mopidy/actor.py
mopidy_mopidy/backend.py
mopidy_mopidy/classes.py
mopidy_mopidy/ext.conf
mopidy_mopidy/library_provider.py
mopidy_mopidy/playback_provider.py
mopidy_mopidy/playlist_provider.py
mopidy_mopidy/test.py
mopidy_mopidy/utils.py
mopidy_mopidy/web.py
mopidy_mopidy.egg-info/PKG-INFO
mopidy_mopidy.egg-info/SOURCES.txt
mopidy_mopidy.egg-info/dependency_links.txt
mopidy_mopidy.egg-info/entry_points.txt
mopidy_mopidy.egg-info/top_level.txt