Metadata-Version: 1.1
Name: mopidy-mopidy
Version: 0.7
Summary: Mopidy satellite extension
Home-page: https://github.com/stffart/mopidy-mopidy
Author: stffart
Author-email: stffart@gmail.com
License: GPLv3
Platform: UNKNOWN
Classifier: Programming Language :: Python :: 3
